AUTHORS
LICENSE
MANIFEST.in
README
setup.py
docs/Makefile
docs/adapters.rst
docs/conf.py
docs/date_splitter.rst
docs/dateglob.rst
docs/file_sources.rst
docs/filters.rst
docs/index.rst
docs/lineformats.rst
docs/sources.rst
docs/utils.rst
examples/service_unavailable.py
examples/logmerge/logmerge.py
examples/logmerge/logs.ini
loglab/__init__.py
loglab/adapters.py
loglab/date_splitter.py
loglab/file_sources.py
loglab/filters.py
loglab/lineformats.py
loglab/lumberjack.py
loglab/magpie.py
loglab/merge.py
loglab/sources.py
loglab/subproc_gzip.py
loglab/tail.py
loglab/utils.py
loglab.egg-info/PKG-INFO
loglab.egg-info/SOURCES.txt
loglab.egg-info/dependency_links.txt
loglab.egg-info/top_level.txt
loglab/dateglob/__init__.py
loglab/dateglob/dateglob.py
loglab/dateglob/tests.py
tests/__init__.py
tests/lumberjacktest.py
tests/magpietests.py