Metadata-Version: 1.1
Name: loglab
Version: 0.1
Summary: Components for parsing and filtering webserver logs
Home-page: http://code.google.com/p/python-loglab/
Author: Daniel Pope
Author-email: lord.mauve@gmail.com
License: UNKNOWN
Platform: UNKNOWN
Classifier: Development Status :: 3 - Alpha
Classifier: Environment :: Console
Classifier: Intended Audience :: Developers
Classifier: License :: OSI Approved :: GNU General Public License v3 or later (GPLv3+)
Classifier: Operating System :: POSIX
Classifier: Programming Language :: Python :: 2
Classifier: Topic :: System :: Logging
